setup.py
pypis3/__init__.py
pypis3/cli.py
pypis3/package.py
pypis3/storage.py
pypis3.egg-info/PKG-INFO
pypis3.egg-info/SOURCES.txt
pypis3.egg-info/dependency_links.txt
pypis3.egg-info/entry_points.txt
pypis3.egg-info/requires.txt
pypis3.egg-info/top_level.txt
pypis3/templates/index.html.j2