Metadata-Version: 1.1
Name: pypis3
Version: 0.1.1
Summary: CLI tool for creating a private Python Package Repository backed entirely by AWS S3 storage
Home-page: https://github.com/JamieCressey/pypis3
Author: Jamie Cressey
Author-email: jamiecressey89@gmail.com
License: UNKNOWN
Download-URL: https://github.com/jamiecressey/pypis3/tarball/0.1.1
Platform: UNKNOWN
